copydetect/__init__.py
copydetect/__main__.py
copydetect/_config.py
copydetect/defaults.py
copydetect/detector.py
copydetect/pywinnow.py
copydetect/utils.py
copydetect/data/__init__.py
copydetect/data/report.html
copydetect-0.5.0.dist-info/LICENSE
copydetect-0.5.0.dist-info/METADATA
copydetect-0.5.0.dist-info/WHEEL
copydetect-0.5.0.dist-info/entry_points.txt
copydetect-0.5.0.dist-info/top_level.txt
copydetect-0.5.0.dist-info/RECORD
