Metadata-Version: 2.1
Name: copydetect
Version: 0.5.0
Summary: Code plagiarism detection tool
Home-page: https://github.com/blingenf/copydetect
Author: Bryson Lingenfelter
Author-email: blingenfelter@nevada.unr.edu
Classifier: Programming Language :: Python :: 3.7
Classifier: Programming Language :: Python :: 3.8
Classifier: Programming Language :: Python :: 3.9
Classifier: Programming Language :: Python :: 3.10
Classifier: Programming Language :: Python :: 3.11
Classifier: Programming Language :: Python :: 3.12
Classifier: Programming Language :: Python :: 3 :: Only
Classifier: License :: OSI Approved :: MIT License
Classifier: Operating System :: OS Independent
Classifier: Development Status :: 4 - Beta
Classifier: Intended Audience :: Education
Requires-Python: >=3.7
License-File: LICENSE
Requires-Dist: numpy
Requires-Dist: matplotlib
Requires-Dist: jinja2
Requires-Dist: pygments
Requires-Dist: tqdm
